savanhdb/__init__.py
savanhdb/eventgridsinkwriter.py
savanhdb-0.1.0.dist-info/METADATA
savanhdb-0.1.0.dist-info/WHEEL
savanhdb-0.1.0.dist-info/top_level.txt
savanhdb-0.1.0.dist-info/RECORD
