Metadata-Version: 2.1
Name: savanhdb
Version: 0.1.0
Summary: Databricks spark Azure packages
Home-page: https://github.com/samvanhoutte/databricks
Author: Sam Vanhoutte
Author-email: sam.vanhoutte@marchitec.be
License: UNKNOWN
Platform: UNKNOWN
Classifier: Programming Language :: Python :: 3
Classifier: License :: OSI Approved :: MIT License
Classifier: Operating System :: OS Independent
Requires-Python: >=3.6
Requires-Dist: azure.eventgrid
Requires-Dist: json
